rishabh_api_interactions/__init__.py
rishabh_api_interactions/api_exec_remote_functions.py
rishabh_api_interactions/api_generateIP.py
rishabh_api_interactions/api_httpservice.py
rishabh_api_interactions/api_server_login.py
rishabh_api_interactions/api_tcp_server.py
rishabh_api_interactions/api_udp_server.py
rishabh_api_interactions-0.0.5.dist-info/LICENSE
rishabh_api_interactions-0.0.5.dist-info/METADATA
rishabh_api_interactions-0.0.5.dist-info/WHEEL
rishabh_api_interactions-0.0.5.dist-info/top_level.txt
rishabh_api_interactions-0.0.5.dist-info/RECORD
