Metadata-Version: 2.1
Name: rishabh-api-interactions
Version: 0.0.5
Summary: Api Package for web interactions
Author: Rishabh Pallod
Author-email: rishabhpallod1@gmail.com
Requires-Python: >=3.6
License-File: LICENSE
